AUTHORS
Changelog
LICENSE
MANIFEST.in
README
README.rst
TODO
setup.cfg
setup.py
cyme/__init__.py
cyme/admin.py
cyme/conf.py
cyme/settings.py
cyme/status.py
cyme/tasks.py
cyme.egg-info/PKG-INFO
cyme.egg-info/SOURCES.txt
cyme.egg-info/dependency_links.txt
cyme.egg-info/entry_points.txt
cyme.egg-info/not-zip-safe
cyme.egg-info/requires.txt
cyme.egg-info/top_level.txt
cyme/api/__init__.py
cyme/api/urls.py
cyme/api/views.py
cyme/api/web.py
cyme/bin/__init__.py
cyme/bin/base.py
cyme/bin/cyme.py
cyme/bin/cyme_branch.py
cyme/bin/cyme_list_branches.py
cyme/branch/__init__.py
cyme/branch/controller.py
cyme/branch/httpd.py
cyme/branch/intsup.py
cyme/branch/managers.py
cyme/branch/metrics.py
cyme/branch/signals.py
cyme/branch/state.py
cyme/branch/supervisor.py
cyme/branch/thread.py
cyme/client/__init__.py
cyme/client/base.py
cyme/management/__init__.py
cyme/management/commands/__init__.py
cyme/management/commands/base.py
cyme/management/commands/cyme.py
cyme/management/commands/cyme_branch.py
cyme/models/__init__.py
cyme/models/managers.py
cyme/tests/__init__.py
cyme/tests/test_branch.py
cyme/tests/test_models.py
cyme/utils/__init__.py
cyme/utils/actors.py
cyme/utils/dictshield.py
docs/Makefile
docs/changelog.rst
docs/conf.py
docs/index.rst
docs/introduction.rst
docs/.static/.keep
docs/.templates/page.html
docs/.templates/sidebarintro.html
docs/.templates/sidebarlogo.html
docs/_ext/applyxrefs.py
docs/_ext/celerydocs.py
docs/_ext/celerydocs.pyc
docs/_ext/literals_to_xrefs.py
docs/_theme/celery/theme.conf
docs/_theme/celery/static/celery.css_t
docs/images/celery-icon-128.png
docs/images/celery-icon-32.png
docs/images/celery-icon-64.png
docs/images/celery_favicon_128.png
docs/images/favicon.ico
docs/images/favicon.png
docs/reference/cyme.api.views.rst
docs/reference/cyme.api.web.rst
docs/reference/cyme.bin.base.rst
docs/reference/cyme.bin.cyme.rst
docs/reference/cyme.bin.cyme_branch.rst
docs/reference/cyme.branch.controller.rst
docs/reference/cyme.branch.httpd.rst
docs/reference/cyme.branch.intsup.rst
docs/reference/cyme.branch.managers.rst
docs/reference/cyme.branch.metrics.rst
docs/reference/cyme.branch.rst
docs/reference/cyme.branch.signals.rst
