Metadata-Version: 1.0
Name: cyme
Version: 0.0.5
Summary: Cyme - Celery instance manager
Home-page: http://celeryproject.org
Author: Ask Solem
Author-email: ask@celeryproject.org
License: BSD
Platform: any
Classifier: Development Status :: 4 - Beta
Classifier: Framework :: Django
Classifier: Operating System :: OS Independent
Classifier: Programming Language :: Python
Classifier: Intended Audience :: Developers
Classifier: License :: OSI Approved :: BSD License
Classifier: Operating System :: POSIX
Classifier: Topic :: Communications
Classifier: Topic :: System :: Distributed Computing
Classifier: Topic :: Software Development :: Libraries :: Python Modules
